miniFasta/__init__.py
miniFasta/_miniFasta.py
miniFasta/_reader.py
miniFasta/_writer.py
miniFasta-3.0.3.dist-info/LICENSE
miniFasta-3.0.3.dist-info/METADATA
miniFasta-3.0.3.dist-info/WHEEL
miniFasta-3.0.3.dist-info/top_level.txt
miniFasta-3.0.3.dist-info/RECORD
