Metadata-Version: 2.1
Name: miniFasta
Version: 3.0.3
Summary: A simple FASTA read and write toolbox for small to medium size projects without dependencies.
Home-page: https://github.com/not-a-feature/miniFASTA
Author: Jules Kreuer / not_a_feature
License: gpl-3.0
Keywords: FASTA,reader,bio,bioinformatics
Platform: unix
Platform: linux
Platform: osx
Platform: cygwin
Platform: win32
Classifier: Programming Language :: Python :: 3
Classifier: Programming Language :: Python :: 3.7
Classifier: Programming Language :: Python :: 3.8
Classifier: Programming Language :: Python :: 3.9
Classifier: Programming Language :: Python :: 3.10
Classifier: Programming Language :: Python :: 3.11
Requires-Python: >=3.7
License-File: LICENSE
Provides-Extra: testing
Requires-Dist: pytest (>=7.1) ; extra == 'testing'
Requires-Dist: pytest-cov (>=4.0) ; extra == 'testing'
Requires-Dist: tox (>=3.24) ; extra == 'testing'
Requires-Dist: black (>=21.1) ; extra == 'testing'
